example/__init__.py
example/example.py
pymysql_extension/__init__.py
pymysql_extension/_sql_object_converter.py
pymysql_extension/_sql_reader.py
pymysql_extension-1.0.0.data/data/README.md
pymysql_extension-1.0.0.dist-info/METADATA
pymysql_extension-1.0.0.dist-info/WHEEL
pymysql_extension-1.0.0.dist-info/top_level.txt
pymysql_extension-1.0.0.dist-info/RECORD
