Metadata-Version: 2.1
Name: pymysql-extension
Version: 1.0.0
Summary: pymysql-extension是一个基于pymysql的扩展，主要是为了解决pymysql在使用过程中的一些不便之处。
Home-page: https://github.com/Joker-desire/pymysql-extension
Author: Joker-desire
Author-email: 2590205729@qq.com
License: MIT Licence
Platform: any
Requires: pymysql
